vm_automation/__init__.py
vm_automation/esxiVm.py
vm_automation/workstationVm.py
vm_automation-0.1.8.dist-info/LICENSE
vm_automation-0.1.8.dist-info/METADATA
vm_automation-0.1.8.dist-info/WHEEL
vm_automation-0.1.8.dist-info/top_level.txt
vm_automation-0.1.8.dist-info/zip-safe
vm_automation-0.1.8.dist-info/RECORD
