Metadata-Version: 2.1
Name: vm-automation
Version: 0.1.8
Summary: Virtual infrastructure automation simplified interaction library
Home-page: http://github.com/rapid7/vm-automation
Author: Metasploit Hackers
Author-email: metasploit-hackers@lists.sourceforge.net
License: Format: http://www.debian.org/doc/packaging-manuals/copyright-format/1.0/
Requires-Dist: pyVmomi
Requires-Dist: paramiko
